{
	"word": "georgian",
	"definitions": [
		{
			"definition": "a native or resident of the American state of Georgia",
			"pos": "noun"
		},
		{
			"definition": "a native or inhabitant of Georgia in Asia",
			"pos": "noun"
		},
		{
			"definition": "a southern Caucasian language with 3 million speakers and a long literary tradition",
			"pos": "noun"
		},
		{
			"definition": "of or relating to the former British colony of Georgia",
			"pos": "adjective"
		},
		{
			"definition": "of or relating to or characteristic of the Asian republic of Georgia or its people or language",
			"pos": "adjective"
		},
		{
			"definition": "of or relating to or characteristic of the American state of Georgia or its inhabitants",
			"pos": "adjective"
		},
		{
			"definition": "of or relating to the Hanoverian kings of England",
			"pos": "adjective"
		}
	]
}