{
	"word": "purl",
	"definitions": [
		{
			"definition": "مشروب مالت"
		},
		{
			"definition": "ابجو داراى ادويه معطر"
		},
		{
			"definition": "گلابتون"
		},
		{
			"definition": "زرى"
		},
		{
			"definition": "کوک برجسته وقلابى"
		},
		{
			"definition": "حاشيه"
		},
		{
			"definition": "حلقه دود يا بخار"
		},
		{
			"definition": "صداى شرشر"
		},
		{
			"definition": "زمزمه اب"
		},
		{
			"definition": "مثل فرفره چرخيدن"
		},
		{
			"definition": "واژگون شدن"
		},
		{
			"definition": "زردوزى کردن"
		},
		{
			"definition": "با شرشرجارى شدن"
		},
		{
			"definition": "حلقه حلقه شدن"
		}
	]
}