{
	"word": "baking",
	"definitions": [
		{
			"definition": "making bread or cake or pastry etc.",
			"pos": "noun"
		},
		{
			"definition": "cooking by dry heat in an oven",
			"pos": "noun"
		},
		{
			"definition": "cook and make edible by putting in a hot oven",
			"pos": "verb"
		},
		{
			"definition": "prepare with dry heat in an oven",
			"pos": "verb"
		},
		{
			"definition": "heat by a natural force",
			"pos": "verb"
		},
		{
			"definition": "be very hot, due to hot weather or exposure to the sun",
			"pos": "verb"
		},
		{
			"definition": "as hot as if in an oven",
			"pos": "adjective"
		}
	]
}