{
	"word": "nail",
	"definitions": [
		{
			"definition": "horny plate covering and protecting part of the dorsal surface of the digits",
			"pos": "noun"
		},
		{
			"definition": "a thin pointed piece of metal that is hammered into materials as a fastener",
			"pos": "noun"
		},
		{
			"definition": "a former unit of length for cloth equal to 1/16 of a yard",
			"pos": "noun"
		},
		{
			"definition": "attach something somewhere by means of nails",
			"pos": "verb"
		},
		{
			"definition": "take into custody",
			"pos": "verb"
		},
		{
			"definition": "hit hard",
			"pos": "verb"
		},
		{
			"definition": "succeed in obtaining a position",
			"pos": "verb"
		},
		{
			"definition": "succeed at easily",
			"pos": "verb"
		},
		{
			"definition": "locate exactly",
			"pos": "verb"
		},
		{
			"definition": "complete a pass",
			"pos": "verb"
		}
	]
}