{
	"word": "jack",
	"definitions": [
		{
			"definition": "a small worthless amount",
			"pos": "noun"
		},
		{
			"definition": "a man who serves as a sailor",
			"pos": "noun"
		},
		{
			"definition": "someone who works with their hands",
			"pos": "noun"
		},
		{
			"definition": "immense East Indian fruit resembling breadfruit",
			"pos": "noun"
		},
		{
			"definition": "a small ball at which players aim in lawn bowling",
			"pos": "noun"
		},
		{
			"definition": "an electrical device consisting of a connector socket designed for the insertion of a plug",
			"pos": "noun"
		},
		{
			"definition": "game equipment consisting of one of several small six-pointed metal pieces that are picked up while bouncing a ball in the game of jacks",
			"pos": "noun"
		},
		{
			"definition": "small flag indicating a ship's nationality",
			"pos": "noun"
		},
		{
			"definition": "one of four face cards in a deck bearing a picture of a young prince",
			"pos": "noun"
		},
		{
			"definition": "tool for exerting pressure or lifting",
			"pos": "noun"
		},
		{
			"definition": "any of several fast-swimming predacious fishes of tropical to warm temperate seas",
			"pos": "noun"
		},
		{
			"definition": "male donkey",
			"pos": "noun"
		},
		{
			"definition": "lift with a special device",
			"pos": "verb"
		},
		{
			"definition": "hunt with a jacklight",
			"pos": "verb"
		}
	]
}