{
	"word": "fuse",
	"definitions": [
		{
			"definition": "an electrical device that can interrupt the flow of electrical current when it is overloaded",
			"pos": "noun"
		},
		{
			"definition": "any igniter that is used to initiate the burning of a propellant",
			"pos": "noun"
		},
		{
			"definition": "mix together different elements",
			"pos": "verb"
		},
		{
			"definition": "become plastic or fluid or liquefied from heat",
			"pos": "verb"
		},
		{
			"definition": "equip with a fuse",
			"pos": "verb"
		},
		{
			"definition": "make liquid or plastic by heating",
			"pos": "verb"
		}
	]
}