{
	"word": "sketch",
	"definitions": [
		{
			"definition": "نقشه تقريبى"
		},
		{
			"definition": "کروکى"
		},
		{
			"definition": "شما"
		},
		{
			"definition": "انگاره"
		},
		{
			"definition": "نقشه ساده"
		},
		{
			"definition": "شرح"
		},
		{
			"definition": "پيش نويس ازمايشى"
		},
		{
			"definition": "زمينه"
		},
		{
			"definition": "ملخص"
		},
		{
			"definition": "مسوده کردن"
		},
		{
			"definition": "پيش نويس چيزى را اماده کردن"
		},
		{
			"definition": "طرح خلاصه"
		},
		{
			"definition": "طراحى کليات"
		}
	]
}