{
	"word": "adjunct",
	"definitions": [
		{
			"definition": "something added to another thing but not an essential part of it",
			"pos": "noun"
		},
		{
			"definition": "a person who is an assistant or subordinate to another",
			"pos": "noun"
		},
		{
			"definition": "a construction that can be used to extend the meaning of a word or phrase but is not one of the main constituents of a sentence",
			"pos": "noun"
		},
		{
			"definition": "furnishing added support",
			"pos": "adjective"
		},
		{
			"definition": "of or relating to a person who is subordinate to another",
			"pos": "adjective"
		}
	]
}