{
	"word": "harris",
	"definitions": [
		{
			"definition": "United States author who wrote the stories about Uncle Remus (1848-1908)",
			"pos": "noun"
		},
		{
			"definition": "United States linguist (born in Ukraine) who developed mathematical linguistics and interpreted speech and writing in a social context (1909-1992)",
			"pos": "noun"
		},
		{
			"definition": "United States diplomat who was instrumental in opening Japan to foreign trade (1804-1878)",
			"pos": "noun"
		},
		{
			"definition": "Irish writer noted for his sexually explicit but unreliable autobiography (1856-1931)",
			"pos": "noun"
		},
		{
			"definition": "British marshal of the Royal Air Force",
			"pos": "noun"
		},
		{
			"definition": "publisher of the first newspaper printed in America (1673-1713)",
			"pos": "noun"
		}
	]
}