{
	"word": "transposition",
	"definitions": [
		{
			"definition": "any abnormal position of the organs of the body",
			"pos": "noun"
		},
		{
			"definition": "an event in which one thing is substituted for another",
			"pos": "noun"
		},
		{
			"definition": "(genetics) a kind of mutation in which a chromosomal segment is transfered to a new position on the same or another chromosome",
			"pos": "noun"
		},
		{
			"definition": "(mathematics) the transfer of a quantity from one side of an equation to the other along with a change of sign",
			"pos": "noun"
		},
		{
			"definition": "(electricity) a rearrangement of the relative positions of power lines in order to minimize the effects of mutual capacitance and inductance",
			"pos": "noun"
		},
		{
			"definition": "the act of reversing the order or place of",
			"pos": "noun"
		},
		{
			"definition": "(music) playing in a different key from the key intended",
			"pos": "noun"
		}
	]
}