{
	"word": "brooding",
	"definitions": [
		{
			"definition": "sitting on eggs so as to hatch them by the warmth of the body",
			"pos": "noun"
		},
		{
			"definition": "persistent morbid meditation on a problem",
			"pos": "noun"
		},
		{
			"definition": "think moodily or anxiously about something",
			"pos": "verb"
		},
		{
			"definition": "hang over, as of something threatening, dark, or menacing",
			"pos": "verb"
		},
		{
			"definition": "be in a huff and display one's displeasure",
			"pos": "verb"
		},
		{
			"definition": "be in a huff",
			"pos": "verb"
		},
		{
			"definition": "sit on (eggs)",
			"pos": "verb"
		},
		{
			"definition": "deeply or seriously thoughtful",
			"pos": "adjective"
		}
	]
}