{
	"word": "fuller",
	"definitions": [
		{
			"definition": "United States jurist and chief justice of the United States Supreme Court (1833-1910)",
			"pos": "noun"
		},
		{
			"definition": "United States architect who invented the geodesic dome (1895-1983)",
			"pos": "noun"
		},
		{
			"definition": "a workman who fulls (cleans and thickens) freshly woven cloth for a living",
			"pos": "noun"
		},
		{
			"definition": "containing as much or as many as is possible or normal",
			"pos": "adjective"
		},
		{
			"definition": "constituting the full quantity or extent",
			"pos": "adjective"
		},
		{
			"definition": "complete in extent or degree and in every particular",
			"pos": "adjective"
		},
		{
			"definition": "filled to satisfaction with food or drink",
			"pos": "adjective"
		},
		{
			"definition": "(of sound) having marked deepness and body",
			"pos": "adjective"
		},
		{
			"definition": "having the normally expected amount",
			"pos": "adjective"
		},
		{
			"definition": "being at a peak or culminating point",
			"pos": "adjective"
		},
		{
			"definition": "having ample fabric",
			"pos": "adjective"
		}
	]
}