{
	"word": "abort",
	"definitions": [
		{
			"definition": "صرف نظر کردن"
		},
		{
			"definition": "سقوط کردن موشک يا هواپيما"
		},
		{
			"definition": "ناموفق"
		},
		{
			"definition": "سقوط کردن"
		},
		{
			"definition": "عدم موفقيت درانجام ماموريت"
		},
		{
			"definition": "بچه انداختن"
		},
		{
			"definition": "سقط کردن"
		},
		{
			"definition": "نارس ماندن"
		},
		{
			"definition": "ريشه نکردن"
		},
		{
			"definition": "عقيم ماندن"
		},
		{
			"definition": "بى نتيجه ماندن"
		}
	]
}