{
	"word": "strung",
	"definitions": [
		{
			"definition": "thread on or as if on a string",
			"pos": "verb"
		},
		{
			"definition": "add as if on a string",
			"pos": "verb"
		},
		{
			"definition": "move or come along",
			"pos": "verb"
		},
		{
			"definition": "stretch out or arrange like a string",
			"pos": "verb"
		},
		{
			"definition": "string together",
			"pos": "verb"
		},
		{
			"definition": "remove the stringy parts of",
			"pos": "verb"
		},
		{
			"definition": "provide with strings",
			"pos": "verb"
		},
		{
			"definition": "that is on a string",
			"pos": "adjective"
		}
	]
}