{
	"word": "queer",
	"definitions": [
		{
			"definition": "offensive term for a homosexual man",
			"pos": "noun"
		},
		{
			"definition": "hinder or prevent (the efforts, plans, or desires) of",
			"pos": "verb"
		},
		{
			"definition": "put in a dangerous, disadvantageous, or difficult position",
			"pos": "verb"
		},
		{
			"definition": "beyond or deviating from the usual or expected",
			"pos": "adjective"
		},
		{
			"definition": "homosexual or arousing homosexual desires",
			"pos": "adjective"
		}
	]
}