{
	"word": "surer",
	"definitions": [
		{
			"definition": "having or feeling no doubt or uncertainty",
			"pos": "adjective"
		},
		{
			"definition": "exercising or taking care great enough to bring assurance",
			"pos": "adjective"
		},
		{
			"definition": "certain to occur",
			"pos": "adjective"
		},
		{
			"definition": "physically secure or dependable",
			"pos": "adjective"
		},
		{
			"definition": "reliable in operation or effect",
			"pos": "adjective"
		},
		{
			"definition": "(of persons) worthy of trust or confidence",
			"pos": "adjective"
		},
		{
			"definition": "infallible or unfailing",
			"pos": "adjective"
		},
		{
			"definition": "certain not to fail",
			"pos": "adjective"
		},
		{
			"definition": "impossible to doubt or dispute",
			"pos": "adjective"
		}
	]
}