{
	"word": "slip",
	"definitions": [
		{
			"definition": "يادداشت"
		},
		{
			"definition": "صورت"
		},
		{
			"definition": "سريدن"
		},
		{
			"definition": "جدا شدن لنگر از زمين"
		},
		{
			"definition": "سرخوردن منحرف شدن از مسير"
		},
		{
			"definition": "لغزش"
		},
		{
			"definition": "خطا"
		},
		{
			"definition": "ليزى"
		},
		{
			"definition": "گمراهى"
		},
		{
			"definition": "قلمه"
		},
		{
			"definition": "سرخورى"
		},
		{
			"definition": "تکه کاغذ"
		},
		{
			"definition": "زير پيراهنى"
		},
		{
			"definition": "ملافه"
		},
		{
			"definition": "روکش"
		},
		{
			"definition": "متکا"
		},
		{
			"definition": "نهال"
		},
		{
			"definition": "اولاد"
		},
		{
			"definition": "نسل"
		},
		{
			"definition": "لغزيدن"
		},
		{
			"definition": "ليز خودن"
		},
		{
			"definition": "گريختن"
		},
		{
			"definition": "سهو کردن"
		},
		{
			"definition": "اشتباه کردن"
		},
		{
			"definition": "از قلم انداختن"
		}
	]
}