{
	"word": "fraud",
	"definitions": [
		{
			"definition": "احتيال"
		},
		{
			"definition": "تدليس جزائى"
		},
		{
			"definition": "تدليس مدنى"
		},
		{
			"definition": "غبن"
		},
		{
			"definition": "سوءاستفاده"
		},
		{
			"definition": "کلاهبردارى"
		},
		{
			"definition": "فريب"
		},
		{
			"definition": "حيله"
		},
		{
			"definition": "(حق ).کلاه بردارى"
		},
		{
			"definition": "تقلب"
		},
		{
			"definition": "فن"
		},
		{
			"definition": "گوش بر"
		},
		{
			"definition": "شياد"
		}
	]
}