{
	"word": "tongue",
	"definitions": [
		{
			"definition": "a mobile mass of muscular tissue covered with mucous membrane and located in the oral cavity",
			"pos": "noun"
		},
		{
			"definition": "a human written or spoken language used by a community",
			"pos": "noun"
		},
		{
			"definition": "any long thin projection that is transient",
			"pos": "noun"
		},
		{
			"definition": "a manner of speaking",
			"pos": "noun"
		},
		{
			"definition": "a narrow strip of land that juts out into the sea",
			"pos": "noun"
		},
		{
			"definition": "the tongue of certain animals used as meat",
			"pos": "noun"
		},
		{
			"definition": "the flap of material under the laces of a shoe or boot",
			"pos": "noun"
		},
		{
			"definition": "metal striker that hangs inside a bell and makes a sound by hitting the side",
			"pos": "noun"
		},
		{
			"definition": "articulate by tonguing, as when playing wind instruments",
			"pos": "verb"
		},
		{
			"definition": "lick or explore with the tongue",
			"pos": "verb"
		}
	]
}