{
	"word": "complication",
	"definitions": [
		{
			"definition": "the act or process of complicating",
			"pos": "noun"
		},
		{
			"definition": "a situation or condition that is complex or confused",
			"pos": "noun"
		},
		{
			"definition": "any disease or disorder that occurs during the course of (or because of) another disease",
			"pos": "noun"
		},
		{
			"definition": "a development that complicates a situation",
			"pos": "noun"
		},
		{
			"definition": "puzzling complexity",
			"pos": "noun"
		}
	]
}