{
	"word": "watch",
	"definitions": [
		{
			"definition": "نگهبانى"
		},
		{
			"definition": "پاس"
		},
		{
			"definition": "نگهبان"
		},
		{
			"definition": "مراقبت کردن مواظبت کردن"
		},
		{
			"definition": "پاييدن"
		},
		{
			"definition": "ديدبان"
		},
		{
			"definition": "مدت کشيک"
		},
		{
			"definition": "ساعت جيبى و مچى"
		},
		{
			"definition": "ساعت"
		},
		{
			"definition": "مراقبت کردن"
		},
		{
			"definition": "مواظب بودن"
		},
		{
			"definition": "بر کسى نظارت کردن"
		},
		{
			"definition": "پاسدارى کردن"
		}
	]
}