{
	"word": "compensate",
	"definitions": [
		{
			"definition": "adjust for",
			"pos": "verb"
		},
		{
			"definition": "make amends for",
			"pos": "verb"
		},
		{
			"definition": "make up for shortcomings or a feeling of inferiority by exaggerating good qualities",
			"pos": "verb"
		},
		{
			"definition": "make reparations or amends for",
			"pos": "verb"
		},
		{
			"definition": "do or give something to somebody in return",
			"pos": "verb"
		},
		{
			"definition": "make payment to",
			"pos": "verb"
		}
	]
}