{
	"word": "pot",
	"definitions": [
		{
			"definition": "metal or earthenware cooking vessel that is usually round and deep",
			"pos": "noun"
		},
		{
			"definition": "a plumbing fixture for defecation and urination",
			"pos": "noun"
		},
		{
			"definition": "the quantity contained in a pot",
			"pos": "noun"
		},
		{
			"definition": "a container in which plants are cultivated",
			"pos": "noun"
		},
		{
			"definition": "(often followed by `of') a large number or amount or extent",
			"pos": "noun"
		},
		{
			"definition": "the cumulative amount involved in a game (such as poker)",
			"pos": "noun"
		},
		{
			"definition": "slang for a paunch",
			"pos": "noun"
		},
		{
			"definition": "a resistor with three terminals, the third being an adjustable center terminal",
			"pos": "noun"
		},
		{
			"definition": "street names for marijuana",
			"pos": "noun"
		},
		{
			"definition": "plant in a pot",
			"pos": "verb"
		}
	]
}