{
	"word": "respite",
	"definitions": [
		{
			"definition": "a (temporary) relief from harm or discomfort",
			"pos": "noun"
		},
		{
			"definition": "a pause from doing something (as work)",
			"pos": "noun"
		},
		{
			"definition": "an interruption in the intensity or amount of something",
			"pos": "noun"
		},
		{
			"definition": "a pause for relaxation",
			"pos": "noun"
		},
		{
			"definition": "the act of reprieving",
			"pos": "noun"
		},
		{
			"definition": "postpone the punishment of a convicted criminal, such as an execution",
			"pos": "verb"
		}
	]
}