{
	"word": "step",
	"definitions": [
		{
			"definition": "گام برداشتن"
		},
		{
			"definition": "با گام پيمودن"
		},
		{
			"definition": "پاشنه کفش"
		},
		{
			"definition": "کف پله"
		},
		{
			"definition": "قراردادن دکل درحفره مخصوص"
		},
		{
			"definition": "گام"
		},
		{
			"definition": "مرحله"
		},
		{
			"definition": "صداى پا"
		},
		{
			"definition": "پله"
		},
		{
			"definition": "رکاب"
		},
		{
			"definition": "پلکان"
		},
		{
			"definition": "رتبه"
		},
		{
			"definition": "درجه"
		},
		{
			"definition": "قدم برداشتن"
		},
		{
			"definition": "قدم زدن"
		}
	]
}