{
	"word": "imprint",
	"definitions": [
		{
			"definition": "a distinctive influence",
			"pos": "noun"
		},
		{
			"definition": "a concavity in a surface produced by pressing",
			"pos": "noun"
		},
		{
			"definition": "an identification of a publisher",
			"pos": "noun"
		},
		{
			"definition": "an impression produced by pressure or printing",
			"pos": "noun"
		},
		{
			"definition": "a device produced by pressure on a surface",
			"pos": "noun"
		},
		{
			"definition": "establish or impress firmly in the mind",
			"pos": "verb"
		},
		{
			"definition": "mark or stamp with or as if with pressure",
			"pos": "verb"
		}
	]
}