{
	"word": "logical",
	"definitions": [
		{
			"definition": "capable of or reflecting the capability for correct and valid reasoning",
			"pos": "adjective"
		},
		{
			"definition": "based on known statements or events or conditions",
			"pos": "adjective"
		},
		{
			"definition": "marked by an orderly, logical, and aesthetically consistent relation of parts",
			"pos": "adjective"
		},
		{
			"definition": "capable of thinking and expressing yourself in a clear and consistent manner",
			"pos": "adjective"
		}
	]
}