{
	"word": "miss",
	"definitions": [
		{
			"definition": "سوتى!"
		},
		{
			"definition": "خطا( بيليارد)"
		},
		{
			"definition": "از دست رفتن"
		},
		{
			"definition": "موفق نشدن"
		},
		{
			"definition": "عدم اصابت گلوله به هدف"
		},
		{
			"definition": ")vi.vt.n.(از دست دادن"
		},
		{
			"definition": "احساس فقدان چيزى راکردن"
		},
		{
			"definition": "گم کردن"
		},
		{
			"definition": "خطا کردن"
		},
		{
			"definition": "نداشتن"
		},
		{
			"definition": "فاقدبودن :)n.(دوشيزه"
		}
	]
}