{
	"word": "transmission",
	"definitions": [
		{
			"definition": "the act of sending a message",
			"pos": "noun"
		},
		{
			"definition": "communication by means of transmitted signals",
			"pos": "noun"
		},
		{
			"definition": "the fraction of radiant energy that passes through a substance",
			"pos": "noun"
		},
		{
			"definition": "an incident in which an infectious disease is transmitted",
			"pos": "noun"
		},
		{
			"definition": "the gears that transmit power from an automobile engine via the driveshaft to the live axle",
			"pos": "noun"
		}
	]
}