{
	"word": "imperial",
	"definitions": [
		{
			"definition": "a small tufted beard worn by Emperor Napoleon III",
			"pos": "noun"
		},
		{
			"definition": "a piece of luggage carried on top of a coach",
			"pos": "noun"
		},
		{
			"definition": "relating to or associated with an empire",
			"pos": "adjective"
		},
		{
			"definition": "of or belonging to the British Imperial System of weights and measures",
			"pos": "adjective"
		},
		{
			"definition": "befitting or belonging to an emperor or empress",
			"pos": "adjective"
		},
		{
			"definition": "belonging to or befitting a supreme ruler",
			"pos": "adjective"
		}
	]
}